main/__init__.py
main/__main__.py
main/config.json
main/server.py
mcp_seedream-1.1.16.dist-info/METADATA
mcp_seedream-1.1.16.dist-info/WHEEL
mcp_seedream-1.1.16.dist-info/entry_points.txt
mcp_seedream-1.1.16.dist-info/licenses/LICENSE
mcp_seedream-1.1.16.dist-info/RECORD
