Metadata-Version: 2.4
Name: mcp-seedream
Version: 1.1.16
Summary: MCP server for Doubao image generation - generates images from text prompts using Doubao's API
Project-URL: Homepage, https://github.com/aardpro/mcp-seedream
Project-URL: Repository, https://github.com/aardpro/mcp-seedream
Project-URL: Issues, https://github.com/aardpro/mcp-seedream/issues
Author-email: aardpro <chileehong@outlook.com>
License-Expression: MIT
License-File: LICENSE
Keywords: ai,api,doubao,image-generation,mcp,mcp-seedream,text-to-image
Classifier: Development Status :: 4 - Beta
Classifier: Intended Audience :: Developers
Classifier: License :: OSI Approved :: MIT License
Classifier: Programming Language :: Python :: 3
Classifier: Programming Language :: Python :: 3.10
Classifier: Programming Language :: Python :: 3.11
Classifier: Programming Language :: Python :: 3.12
Requires-Python: >=3.10
Requires-Dist: mcp>=1.0.0
Requires-Dist: minio>=7.2.7
Requires-Dist: openai>=1.3.7
Requires-Dist: requests>=2.31.0
Provides-Extra: dev
Requires-Dist: pytest>=7.0.0; extra == 'dev'
Requires-Dist: ruff>=0.1.0; extra == 'dev'
